{
  "FaceDetails": [
    {
      "BoundingBox": {
        "Width": 0.09892492741346359,
        "Height": 0.21225301921367645,
        "Left": 0.6103245615959167,
        "Top": 0.4116094410419464
      },
      "AgeRange": {
        "Low": 20,
        "High": 28
      },
      "Smile": {
        "Value": false,
        "Confidence": 94.12409973144531
      },
      "Eyeglasses": {
        "Value": false,
        "Confidence": 97.06620788574219
      },
      "Sunglasses": {
        "Value": false,
        "Confidence": 99.99639129638672
      },
      "Gender": {
        "Value": "Male",
        "Confidence": 99.29684448242188
      },
      "Beard": {
        "Value": false,
        "Confidence": 84.01335906982422
      },
      "Mustache": {
        "Value": false,
        "Confidence": 97.16542053222656
      },
      "EyesOpen": {
        "Value": true,
        "Confidence": 97.91060638427734
      },
      "MouthOpen": {
        "Value": false,
        "Confidence": 61.149776458740234
      },
      "Emotions": [
        {
          "Type": "CALM",
          "Confidence": 63.729713439941406
        },
        {
          "Type": "ANGRY",
          "Confidence": 18.618005752563477
        },
        {
          "Type": "SURPRISED",
          "Confidence": 13.934141159057617
        },
        {
          "Type": "FEAR",
          "Confidence": 6.1811442375183105
        },
        {
          "Type": "SAD",
          "Confidence": 2.852358818054199
        },
        {
          "Type": "HAPPY",
          "Confidence": 2.3378562927246094
        },
        {
          "Type": "CONFUSED",
          "Confidence": 1.1670544147491455
        },
        {
          "Type": "DISGUSTED",
          "Confidence": 1.0070632696151733
        }
      ],
      "Landmarks": [
        {
          "Type": "eyeLeft",
          "X": 0.6521349549293518,
          "Y": 0.4844408929347992
        },
        {
          "Type": "eyeRight",
          "X": 0.6920498609542847,
          "Y": 0.486324280500412
        },
        {
          "Type": "mouthLeft",
          "X": 0.6548193693161011,
          "Y": 0.5607492327690125
        },
        {
          "Type": "mouthRight",
          "X": 0.6881901621818542,
          "Y": 0.5620696544647217
        },
        {
          "Type": "nose",
          "X": 0.6833293437957764,
          "Y": 0.525268018245697
        },
        {
          "Type": "leftEyeBrowLeft",
          "X": 0.6327912211418152,
          "Y": 0.467460572719574
        },
        {
          "Type": "leftEyeBrowRight",
          "X": 0.664444088935852,
          "Y": 0.46275296807289124
        },
        {
          "Type": "leftEyeBrowUp",
          "X": 0.6506538987159729,
          "Y": 0.45842137932777405
        },
        {
          "Type": "rightEyeBrowLeft",
          "X": 0.6875290274620056,
          "Y": 0.46407550573349
        },
        {
          "Type": "rightEyeBrowRight",
          "X": 0.7025204300880432,
          "Y": 0.4707152843475342
        },
        {
          "Type": "rightEyeBrowUp",
          "X": 0.6970983147621155,
          "Y": 0.4608939290046692
        },
        {
          "Type": "leftEyeLeft",
          "X": 0.6433413624763489,
          "Y": 0.4840545356273651
        },
        {
          "Type": "leftEyeRight",
          "X": 0.6598142981529236,
          "Y": 0.48570945858955383
        },
        {
          "Type": "leftEyeUp",
          "X": 0.652542233467102,
          "Y": 0.4807099997997284
        },
        {
          "Type": "leftEyeDown",
          "X": 0.6521437168121338,
          "Y": 0.4879968464374542
        },
        {
          "Type": "rightEyeLeft",
          "X": 0.6839463114738464,
          "Y": 0.48689374327659607
        },
        {
          "Type": "rightEyeRight",
          "X": 0.6976048946380615,
          "Y": 0.4864915907382965
        },
        {
          "Type": "rightEyeUp",
          "X": 0.6927198171615601,
          "Y": 0.482634037733078
        },
        {
          "Type": "rightEyeDown",
          "X": 0.691772997379303,
          "Y": 0.4897632896900177
        },
        {
          "Type": "noseLeft",
          "X": 0.6680957674980164,
          "Y": 0.5336488485336304
        },
        {
          "Type": "noseRight",
          "X": 0.6830825209617615,
          "Y": 0.53424471616745
        },
        {
          "Type": "mouthUp",
          "X": 0.6764336228370667,
          "Y": 0.5517412424087524
        },
        {
          "Type": "mouthDown",
          "X": 0.6744317412376404,
          "Y": 0.5745725035667419
        },
        {
          "Type": "leftPupil",
          "X": 0.6521349549293518,
          "Y": 0.4844408929347992
        },
        {
          "Type": "rightPupil",
          "X": 0.6920498609542847,
          "Y": 0.486324280500412
        },
        {
          "Type": "upperJawlineLeft",
          "X": 0.6094662547111511,
          "Y": 0.48681640625
        },
        {
          "Type": "midJawlineLeft",
          "X": 0.6187900900840759,
          "Y": 0.5676396489143372
        },
        {
          "Type": "chinBottom",
          "X": 0.6687361001968384,
          "Y": 0.6132723689079285
        },
        {
          "Type": "midJawlineRight",
          "X": 0.690409243106842,
          "Y": 0.5704889893531799
        },
        {
          "Type": "upperJawlineRight",
          "X": 0.6972853541374207,
          "Y": 0.49093687534332275
        }
      ],
      "Pose": {
        "Roll": 2.4614510536193848,
        "Yaw": 19.33297348022461,
        "Pitch": 1.0068271160125732
      },
      "Quality": {
        "Brightness": 79.45716094970703,
        "Sharpness": 20.927310943603516
      },
      "Confidence": 99.992431640625
    },
    {
      "BoundingBox": {
        "Width": 0.10790358483791351,
        "Height": 0.18584711849689484,
        "Left": 0.21133694052696228,
        "Top": 0.5053024291992188
      },
      "AgeRange": {
        "Low": 52,
        "High": 60
      },
      "Smile": {
        "Value": false,
        "Confidence": 94.28453826904297
      },
      "Eyeglasses": {
        "Value": false,
        "Confidence": 97.13088989257812
      },
      "Sunglasses": {
        "Value": false,
        "Confidence": 99.99639129638672
      },
      "Gender": {
        "Value": "Male",
        "Confidence": 96.8818588256836
      },
      "Beard": {
        "Value": false,
        "Confidence": 61.677024841308594
      },
      "Mustache": {
        "Value": false,
        "Confidence": 94.77056121826172
      },
      "EyesOpen": {
        "Value": true,
        "Confidence": 71.09288024902344
      },
      "MouthOpen": {
        "Value": false,
        "Confidence": 87.21436309814453
      },
      "Emotions": [
        {
          "Type": "CALM",
          "Confidence": 82.29368591308594
        },
        {
          "Type": "ANGRY",
          "Confidence": 11.545388221740723
        },
        {
          "Type": "SURPRISED",
          "Confidence": 6.822074890136719
        },
        {
          "Type": "FEAR",
          "Confidence": 5.976739883422852
        },
        {
          "Type": "SAD",
          "Confidence": 2.696751356124878
        },
        {
          "Type": "DISGUSTED",
          "Confidence": 1.858307957649231
        },
        {
          "Type": "HAPPY",
          "Confidence": 0.6809709668159485
        },
        {
          "Type": "CONFUSED",
          "Confidence": 0.6290400624275208
        }
      ],
      "Landmarks": [
        {
          "Type": "eyeLeft",
          "X": 0.2437245398759842,
          "Y": 0.5650173425674438
        },
        {
          "Type": "eyeRight",
          "X": 0.2894440293312073,
          "Y": 0.5560274720191956
        },
        {
          "Type": "mouthLeft",
          "X": 0.2525569200515747,
          "Y": 0.6442402601242065
        },
        {
          "Type": "mouthRight",
          "X": 0.2910313308238983,
          "Y": 0.6366662383079529
        },
        {
          "Type": "nose",
          "X": 0.2722056806087494,
          "Y": 0.6070502996444702
        },
        {
          "Type": "leftEyeBrowLeft",
          "X": 0.22429533302783966,
          "Y": 0.5499101281166077
        },
        {
          "Type": "leftEyeBrowRight",
          "X": 0.252557635307312,
          "Y": 0.5415294766426086
        },
        {
          "Type": "leftEyeBrowUp",
          "X": 0.23850777745246887,
          "Y": 0.5393567085266113
        },
        {
          "Type": "rightEyeBrowLeft",
          "X": 0.2787333130836487,
          "Y": 0.5364524722099304
        },
        {
          "Type": "rightEyeBrowRight",
          "X": 0.3035195469856262,
          "Y": 0.5341965556144714
        },
        {
          "Type": "rightEyeBrowUp",
          "X": 0.29114729166030884,
          "Y": 0.5290831923484802
        },
        {
          "Type": "leftEyeLeft",
          "X": 0.23510156571865082,
          "Y": 0.5660467743873596
        },
        {
          "Type": "leftEyeRight",
          "X": 0.2527157664299011,
          "Y": 0.564320981502533
        },
        {
          "Type": "leftEyeUp",
          "X": 0.2434268295764923,
          "Y": 0.5613828301429749
        },
        {
          "Type": "leftEyeDown",
          "X": 0.24407072365283966,
          "Y": 0.5688088536262512
        },
        {
          "Type": "rightEyeLeft",
          "X": 0.28029218316078186,
          "Y": 0.5588840246200562
        },
        {
          "Type": "rightEyeRight",
          "X": 0.29705536365509033,
          "Y": 0.5538477897644043
        },
        {
          "Type": "rightEyeUp",
          "X": 0.2893293797969818,
          "Y": 0.5523586869239807
        },
        {
          "Type": "rightEyeDown",
          "X": 0.2893710732460022,
          "Y": 0.5598757266998291
        },
        {
          "Type": "noseLeft",
          "X": 0.2621927261352539,
          "Y": 0.6155030727386475
        },
        {
          "Type": "noseRight",
          "X": 0.2791694700717926,
          "Y": 0.6121779084205627
        },
        {
          "Type": "mouthUp",
          "X": 0.2722029685974121,
          "Y": 0.632925271987915
        },
        {
          "Type": "mouthDown",
          "X": 0.2732989192008972,
          "Y": 0.6566359996795654
        },
        {
          "Type": "leftPupil",
          "X": 0.2437245398759842,
          "Y": 0.5650173425674438
        },
        {
          "Type": "rightPupil",
          "X": 0.2894440293312073,
          "Y": 0.5560274720191956
        },
        {
          "Type": "upperJawlineLeft",
          "X": 0.2119545340538025,
          "Y": 0.5677927136421204
        },
        {
          "Type": "midJawlineLeft",
          "X": 0.22752346098423004,
          "Y": 0.6516296863555908
        },
        {
          "Type": "chinBottom",
          "X": 0.27473020553588867,
          "Y": 0.6958090662956238
        },
        {
          "Type": "midJawlineRight",
          "X": 0.3082422614097595,
          "Y": 0.6356526613235474
        },
        {
          "Type": "upperJawlineRight",
          "X": 0.31125912070274353,
          "Y": 0.5481337308883667
        }
      ],
      "Pose": {
        "Roll": -8.813197135925293,
        "Yaw": 5.547313213348389,
        "Pitch": -4.826739311218262
      },
      "Quality": {
        "Brightness": 36.598731994628906,
        "Sharpness": 12.848764419555664
      },
      "Confidence": 99.95368957519531
    },
    {
      "BoundingBox": {
        "Width": 0.045368608087301254,
        "Height": 0.08930722624063492,
        "Left": 0.8567643165588379,
        "Top": 0.35109975934028625
      },
      "AgeRange": {
        "Low": 26,
        "High": 36
      },
      "Smile": {
        "Value": false,
        "Confidence": 90.36271667480469
      },
      "Eyeglasses": {
        "Value": true,
        "Confidence": 70.53007507324219
      },
      "Sunglasses": {
        "Value": false,
        "Confidence": 99.98208618164062
      },
      "Gender": {
        "Value": "Female",
        "Confidence": 75.5935287475586
      },
      "Beard": {
        "Value": false,
        "Confidence": 61.256622314453125
      },
      "Mustache": {
        "Value": false,
        "Confidence": 92.90760803222656
      },
      "EyesOpen": {
        "Value": false,
        "Confidence": 77.48697662353516
      },
      "MouthOpen": {
        "Value": false,
        "Confidence": 80.72974395751953
      },
      "Emotions": [
        {
          "Type": "SAD",
          "Confidence": 99.99651336669922
        },
        {
          "Type": "SURPRISED",
          "Confidence": 6.276238918304443
        },
        {
          "Type": "FEAR",
          "Confidence": 6.053600311279297
        },
        {
          "Type": "ANGRY",
          "Confidence": 0.32645776867866516
        },
        {
          "Type": "DISGUSTED",
          "Confidence": 0.30826711654663086
        },
        {
          "Type": "CALM",
          "Confidence": 0.14475274085998535
        },
        {
          "Type": "CONFUSED",
          "Confidence": 0.05810610577464104
        },
        {
          "Type": "HAPPY",
          "Confidence": 0.05088922753930092
        }
      ],
      "Landmarks": [
        {
          "Type": "eyeLeft",
          "X": 0.8658282160758972,
          "Y": 0.38436612486839294
        },
        {
          "Type": "eyeRight",
          "X": 0.88442063331604,
          "Y": 0.385161429643631
        },
        {
          "Type": "mouthLeft",
          "X": 0.8689590096473694,
          "Y": 0.4168974459171295
        },
        {
          "Type": "mouthRight",
          "X": 0.8845916986465454,
          "Y": 0.4177146553993225
        },
        {
          "Type": "nose",
          "X": 0.8730058073997498,
          "Y": 0.4075644612312317
        },
        {
          "Type": "leftEyeBrowLeft",
          "X": 0.8596480488777161,
          "Y": 0.3750642240047455
        },
        {
          "Type": "leftEyeBrowRight",
          "X": 0.8682904839515686,
          "Y": 0.37702807784080505
        },
        {
          "Type": "leftEyeBrowUp",
          "X": 0.8633779287338257,
          "Y": 0.37421715259552
        },
        {
          "Type": "rightEyeBrowLeft",
          "X": 0.8789065480232239,
          "Y": 0.3772680461406708
        },
        {
          "Type": "rightEyeBrowRight",
          "X": 0.8919212222099304,
          "Y": 0.3760785758495331
        },
        {
          "Type": "rightEyeBrowUp",
          "X": 0.8847668170928955,
          "Y": 0.37473613023757935
        },
        {
          "Type": "leftEyeLeft",
          "X": 0.8628763556480408,
          "Y": 0.38347721099853516
        },
        {
          "Type": "leftEyeRight",
          "X": 0.8695398569107056,
          "Y": 0.3848778307437897
        },
        {
          "Type": "leftEyeUp",
          "X": 0.8655422329902649,
          "Y": 0.3830655515193939
        },
        {
          "Type": "leftEyeDown",
          "X": 0.8659478425979614,
          "Y": 0.38588011264801025
        },
        {
          "Type": "rightEyeLeft",
          "X": 0.8807495832443237,
          "Y": 0.385314404964447
        },
        {
          "Type": "rightEyeRight",
          "X": 0.8880953192710876,
          "Y": 0.3844509720802307
        },
        {
          "Type": "rightEyeUp",
          "X": 0.8842082023620605,
          "Y": 0.3837859630584717
        },
        {
          "Type": "rightEyeDown",
          "X": 0.8843867778778076,
          "Y": 0.386622816324234
        },
        {
          "Type": "noseLeft",
          "X": 0.8713924288749695,
          "Y": 0.4076354205608368
        },
        {
          "Type": "noseRight",
          "X": 0.8783105611801147,
          "Y": 0.40782415866851807
        },
        {
          "Type": "mouthUp",
          "X": 0.8749618530273438,
          "Y": 0.41585174202919006
        },
        {
          "Type": "mouthDown",
          "X": 0.8758102059364319,
          "Y": 0.4248398542404175
        },
        {
          "Type": "leftPupil",
          "X": 0.8658282160758972,
          "Y": 0.38436612486839294
        },
        {
          "Type": "rightPupil",
          "X": 0.88442063331604,
          "Y": 0.385161429643631
        },
        {
          "Type": "upperJawlineLeft",
          "X": 0.8595123887062073,
          "Y": 0.37680527567863464
        },
        {
          "Type": "midJawlineLeft",
          "X": 0.8641964793205261,
          "Y": 0.4125719368457794
        },
        {
          "Type": "chinBottom",
          "X": 0.8778172135353088,
          "Y": 0.43903908133506775
        },
        {
          "Type": "midJawlineRight",
          "X": 0.8971567153930664,
          "Y": 0.4132557511329651
        },
        {
          "Type": "upperJawlineRight",
          "X": 0.8999854326248169,
          "Y": 0.37775641679763794
        }
      ],
      "Pose": {
        "Roll": -3.0448789596557617,
        "Yaw": -14.515806198120117,
        "Pitch": -10.183506965637207
      },
      "Quality": {
        "Brightness": 42.23133850097656,
        "Sharpness": 1.8666280508041382
      },
      "Confidence": 99.88372039794922
    },
    {
      "BoundingBox": {
        "Width": 0.028400300070643425,
        "Height": 0.07344205677509308,
        "Left": 0.9704397916793823,
        "Top": 0.35842639207839966
      },
      "AgeRange": {
        "Low": 23,
        "High": 33
      },
      "Smile": {
        "Value": false,
        "Confidence": 88.19099426269531
      },
      "Eyeglasses": {
        "Value": true,
        "Confidence": 70.69332885742188
      },
      "Sunglasses": {
        "Value": false,
        "Confidence": 99.96141052246094
      },
      "Gender": {
        "Value": "Male",
        "Confidence": 91.1368179321289
      },
      "Beard": {
        "Value": true,
        "Confidence": 79.73538208007812
      },
      "Mustache": {
        "Value": false,
        "Confidence": 86.49467468261719
      },
      "EyesOpen": {
        "Value": true,
        "Confidence": 96.24471282958984
      },
      "MouthOpen": {
        "Value": false,
        "Confidence": 80.54015350341797
      },
      "Emotions": [
        {
          "Type": "SAD",
          "Confidence": 81.23493957519531
        },
        {
          "Type": "ANGRY",
          "Confidence": 33.40964889526367
        },
        {
          "Type": "CALM",
          "Confidence": 9.202611923217773
        },
        {
          "Type": "DISGUSTED",
          "Confidence": 8.289088249206543
        },
        {
          "Type": "FEAR",
          "Confidence": 7.606658935546875
        },
        {
          "Type": "SURPRISED",
          "Confidence": 6.736111640930176
        },
        {
          "Type": "HAPPY",
          "Confidence": 4.632431507110596
        },
        {
          "Type": "CONFUSED",
          "Confidence": 2.4195926189422607
        }
      ],
      "Landmarks": [
        {
          "Type": "eyeLeft",
          "X": 0.9766622185707092,
          "Y": 0.38613712787628174
        },
        {
          "Type": "eyeRight",
          "X": 0.993895947933197,
          "Y": 0.38896363973617554
        },
        {
          "Type": "mouthLeft",
          "X": 0.9776118993759155,
          "Y": 0.4198623299598694
        },
        {
          "Type": "mouthRight",
          "X": 0.9920923113822937,
          "Y": 0.4222155511379242
        },
        {
          "Type": "nose",
          "X": 0.9855284690856934,
          "Y": 0.4108927249908447
        },
        {
          "Type": "leftEyeBrowLeft",
          "X": 0.9701919555664062,
          "Y": 0.37599676847457886
        },
        {
          "Type": "leftEyeBrowRight",
          "X": 0.9806209206581116,
          "Y": 0.37915804982185364
        },
        {
          "Type": "leftEyeBrowUp",
          "X": 0.9755412936210632,
          "Y": 0.37567514181137085
        },
        {
          "Type": "rightEyeBrowLeft",
          "X": 0.9905320405960083,
          "Y": 0.38069114089012146
        },
        {
          "Type": "rightEyeBrowRight",
          "X": 1.0002472400665283,
          "Y": 0.38071727752685547
        },
        {
          "Type": "rightEyeBrowUp",
          "X": 0.9955096244812012,
          "Y": 0.37876391410827637
        },
        {
          "Type": "leftEyeLeft",
          "X": 0.9734853506088257,
          "Y": 0.3849064111709595
        },
        {
          "Type": "leftEyeRight",
          "X": 0.9800688028335571,
          "Y": 0.3870896100997925
        },
        {
          "Type": "leftEyeUp",
          "X": 0.9766488075256348,
          "Y": 0.384816974401474
        },
        {
          "Type": "leftEyeDown",
          "X": 0.9766877889633179,
          "Y": 0.38772842288017273
        },
        {
          "Type": "rightEyeLeft",
          "X": 0.9904728531837463,
          "Y": 0.3887841999530792
        },
        {
          "Type": "rightEyeRight",
          "X": 0.9969229698181152,
          "Y": 0.38865628838539124
        },
        {
          "Type": "rightEyeUp",
          "X": 0.9939834475517273,
          "Y": 0.38761472702026367
        },
        {
          "Type": "rightEyeDown",
          "X": 0.9938128590583801,
          "Y": 0.3904798924922943
        },
        {
          "Type": "noseLeft",
          "X": 0.9817917346954346,
          "Y": 0.4105590283870697
        },
        {
          "Type": "noseRight",
          "X": 0.9882738590240479,
          "Y": 0.4115201234817505
        },
        {
          "Type": "mouthUp",
          "X": 0.9849517345428467,
          "Y": 0.4193246066570282
        },
        {
          "Type": "mouthDown",
          "X": 0.9846900105476379,
          "Y": 0.42850029468536377
        },
        {
          "Type": "leftPupil",
          "X": 0.9766622185707092,
          "Y": 0.38613712787628174
        },
        {
          "Type": "rightPupil",
          "X": 0.993895947933197,
          "Y": 0.38896363973617554
        },
        {
          "Type": "upperJawlineLeft",
          "X": 0.9656153917312622,
          "Y": 0.37737172842025757
        },
        {
          "Type": "midJawlineLeft",
          "X": 0.9684200882911682,
          "Y": 0.414061963558197
        },
        {
          "Type": "chinBottom",
          "X": 0.9841081500053406,
          "Y": 0.44285327196121216
        },
        {
          "Type": "midJawlineRight",
          "X": 0.9993466138839722,
          "Y": 0.4186100363731384
        },
        {
          "Type": "upperJawlineRight",
          "X": 1.0034416913986206,
          "Y": 0.383149117231369
        }
      ],
      "Pose": {
        "Roll": 6.464126110076904,
        "Yaw": -7.854872703552246,
        "Pitch": -24.210603713989258
      },
      "Quality": {
        "Brightness": 49.9731330871582,
        "Sharpness": 1.0484901666641235
      },
      "Confidence": 91.41836547851562
    },
    {
      "BoundingBox": {
        "Width": 0.01166483573615551,
        "Height": 0.021888524293899536,
        "Left": 0.7541021108627319,
        "Top": 0.23529912531375885
      },
      "AgeRange": {
        "Low": 21,
        "High": 29
      },
      "Smile": {
        "Value": false,
        "Confidence": 94.30793762207031
      },
      "Eyeglasses": {
        "Value": false,
        "Confidence": 95.86447143554688
      },
      "Sunglasses": {
        "Value": false,
        "Confidence": 99.99543762207031
      },
      "Gender": {
        "Value": "Male",
        "Confidence": 98.90140533447266
      },
      "Beard": {
        "Value": false,
        "Confidence": 72.00868225097656
      },
      "Mustache": {
        "Value": false,
        "Confidence": 95.12904357910156
      },
      "EyesOpen": {
        "Value": false,
        "Confidence": 53.60382843017578
      },
      "MouthOpen": {
        "Value": false,
        "Confidence": 90.56002807617188
      },
      "Emotions": [
        {
          "Type": "CALM",
          "Confidence": 97.0180435180664
        },
        {
          "Type": "SURPRISED",
          "Confidence": 6.3494720458984375
        },
        {
          "Type": "FEAR",
          "Confidence": 6.0509843826293945
        },
        {
          "Type": "SAD",
          "Confidence": 2.2825734615325928
        },
        {
          "Type": "CONFUSED",
          "Confidence": 1.0273566246032715
        },
        {
          "Type": "DISGUSTED",
          "Confidence": 0.4921949803829193
        },
        {
          "Type": "ANGRY",
          "Confidence": 0.2444191873073578
        },
        {
          "Type": "HAPPY",
          "Confidence": 0.11868288367986679
        }
      ],
      "Landmarks": [
        {
          "Type": "eyeLeft",
          "X": 0.7629926800727844,
          "Y": 0.24658627808094025
        },
        {
          "Type": "eyeRight",
          "X": 0.7620059251785278,
          "Y": 0.24686433374881744
        },
        {
          "Type": "mouthLeft",
          "X": 0.7626412510871887,
          "Y": 0.24490676820278168
        },
        {
          "Type": "mouthRight",
          "X": 0.7618463635444641,
          "Y": 0.2451058179140091
        },
        {
          "Type": "nose",
          "X": 0.7636687755584717,
          "Y": 0.24583111703395844
        },
        {
          "Type": "leftEyeBrowLeft",
          "X": 0.762921154499054,
          "Y": 0.24699543416500092
        },
        {
          "Type": "leftEyeBrowRight",
          "X": 0.763286292552948,
          "Y": 0.24720193445682526
        },
        {
          "Type": "leftEyeBrowUp",
          "X": 0.7633507251739502,
          "Y": 0.24721738696098328
        },
        {
          "Type": "rightEyeBrowLeft",
          "X": 0.7627127170562744,
          "Y": 0.2473970651626587
        },
        {
          "Type": "rightEyeBrowRight",
          "X": 0.7611556053161621,
          "Y": 0.2474864423274994
        },
        {
          "Type": "rightEyeBrowUp",
          "X": 0.7621862292289734,
          "Y": 0.24758583307266235
        },
        {
          "Type": "leftEyeLeft",
          "X": 0.7629944086074829,
          "Y": 0.2465825080871582
        },
        {
          "Type": "leftEyeRight",
          "X": 0.7627763748168945,
          "Y": 0.2466610223054886
        },
        {
          "Type": "leftEyeUp",
          "X": 0.7630710601806641,
          "Y": 0.2466847002506256
        },
        {
          "Type": "leftEyeDown",
          "X": 0.7629697322845459,
          "Y": 0.24654652178287506
        },
        {
          "Type": "rightEyeLeft",
          "X": 0.7621757388114929,
          "Y": 0.24683399498462677
        },
        {
          "Type": "rightEyeRight",
          "X": 0.7616444826126099,
          "Y": 0.2469496876001358
        },
        {
          "Type": "rightEyeUp",
          "X": 0.762074887752533,
          "Y": 0.24697044491767883
        },
        {
          "Type": "rightEyeDown",
          "X": 0.761987566947937,
          "Y": 0.24681277573108673
        },
        {
          "Type": "noseLeft",
          "X": 0.7629826664924622,
          "Y": 0.2456377148628235
        },
        {
          "Type": "noseRight",
          "X": 0.7626093029975891,
          "Y": 0.24573397636413574
        },
        {
          "Type": "mouthUp",
          "X": 0.7628495097160339,
          "Y": 0.24525600671768188
        },
        {
          "Type": "mouthDown",
          "X": 0.7625674605369568,
          "Y": 0.24477791786193848
        },
        {
          "Type": "leftPupil",
          "X": 0.7629926800727844,
          "Y": 0.24658627808094025
        },
        {
          "Type": "rightPupil",
          "X": 0.7620059251785278,
          "Y": 0.24686433374881744
        },
        {
          "Type": "upperJawlineLeft",
          "X": 0.7615038156509399,
          "Y": 0.24661535024642944
        },
        {
          "Type": "midJawlineLeft",
          "X": 0.7612585425376892,
          "Y": 0.2447787970304489
        },
        {
          "Type": "chinBottom",
          "X": 0.7618398666381836,
          "Y": 0.24390067160129547
        },
        {
          "Type": "midJawlineRight",
          "X": 0.7594184875488281,
          "Y": 0.24524393677711487
        },
        {
          "Type": "upperJawlineRight",
          "X": 0.7592546343803406,
          "Y": 0.24724993109703064
        }
      ],
      "Pose": {
        "Roll": 4.483348369598389,
        "Yaw": -0.6720097064971924,
        "Pitch": -3.603644847869873
      },
      "Quality": {
        "Brightness": 29.12388801574707,
        "Sharpness": 0.4386158287525177
      },
      "Confidence": 71.6335678100586
    },
    {
      "BoundingBox": {
        "Width": 0.009930473752319813,
        "Height": 0.020679965615272522,
        "Left": 0.5551285743713379,
        "Top": 0.47738027572631836
      },
      "AgeRange": {
        "Low": 24,
        "High": 34
      },
      "Smile": {
        "Value": false,
        "Confidence": 92.50331115722656
      },
      "Eyeglasses": {
        "Value": false,
        "Confidence": 74.44502258300781
      },
      "Sunglasses": {
        "Value": false,
        "Confidence": 99.98632049560547
      },
      "Gender": {
        "Value": "Male",
        "Confidence": 86.1834945678711
      },
      "Beard": {
        "Value": true,
        "Confidence": 55.858909606933594
      },
      "Mustache": {
        "Value": false,
        "Confidence": 80.33126831054688
      },
      "EyesOpen": {
        "Value": true,
        "Confidence": 67.07157135009766
      },
      "MouthOpen": {
        "Value": false,
        "Confidence": 76.49088287353516
      },
      "Emotions": [
        {
          "Type": "CONFUSED",
          "Confidence": 58.765472412109375
        },
        {
          "Type": "ANGRY",
          "Confidence": 11.990228652954102
        },
        {
          "Type": "SURPRISED",
          "Confidence": 10.726332664489746
        },
        {
          "Type": "FEAR",
          "Confidence": 9.797656059265137
        },
        {
          "Type": "CALM",
          "Confidence": 7.068329334259033
        },
        {
          "Type": "SAD",
          "Confidence": 4.326206207275391
        },
        {
          "Type": "DISGUSTED",
          "Confidence": 1.3054739236831665
        },
        {
          "Type": "HAPPY",
          "Confidence": 0.7222263813018799
        }
      ],
      "Landmarks": [
        {
          "Type": "eyeLeft",
          "X": 0.5566689968109131,
          "Y": 0.48642125725746155
        },
        {
          "Type": "eyeRight",
          "X": 0.5600599646568298,
          "Y": 0.48639577627182007
        },
        {
          "Type": "mouthLeft",
          "X": 0.5571967363357544,
          "Y": 0.49636322259902954
        },
        {
          "Type": "mouthRight",
          "X": 0.56001216173172,
          "Y": 0.4963894486427307
        },
        {
          "Type": "nose",
          "X": 0.556754469871521,
          "Y": 0.4920176565647125
        },
        {
          "Type": "leftEyeBrowLeft",
          "X": 0.5561110377311707,
          "Y": 0.48431408405303955
        },
        {
          "Type": "leftEyeBrowRight",
          "X": 0.5568100810050964,
          "Y": 0.4839143455028534
        },
        {
          "Type": "leftEyeBrowUp",
          "X": 0.5561128854751587,
          "Y": 0.4833783209323883
        },
        {
          "Type": "rightEyeBrowLeft",
          "X": 0.5588241219520569,
          "Y": 0.48386889696121216
        },
        {
          "Type": "rightEyeBrowRight",
          "X": 0.5621320009231567,
          "Y": 0.4843274652957916
        },
        {
          "Type": "rightEyeBrowUp",
          "X": 0.5601707696914673,
          "Y": 0.4833264946937561
        },
        {
          "Type": "leftEyeLeft",
          "X": 0.5563256144523621,
          "Y": 0.4863854944705963
        },
        {
          "Type": "leftEyeRight",
          "X": 0.557415246963501,
          "Y": 0.48657527565956116
        },
        {
          "Type": "leftEyeUp",
          "X": 0.5565845966339111,
          "Y": 0.4859877824783325
        },
        {
          "Type": "leftEyeDown",
          "X": 0.5567277073860168,
          "Y": 0.48688679933547974
        },
        {
          "Type": "rightEyeLeft",
          "X": 0.5594692230224609,
          "Y": 0.4865637421607971
        },
        {
          "Type": "rightEyeRight",
          "X": 0.560982346534729,
          "Y": 0.48637568950653076
        },
        {
          "Type": "rightEyeUp",
          "X": 0.5600185990333557,
          "Y": 0.4859660565853119
        },
        {
          "Type": "rightEyeDown",
          "X": 0.5601184368133545,
          "Y": 0.4868808388710022
        },
        {
          "Type": "noseLeft",
          "X": 0.5572974681854248,
          "Y": 0.49272727966308594
        },
        {
          "Type": "noseRight",
          "X": 0.5586273670196533,
          "Y": 0.49273887276649475
        },
        {
          "Type": "mouthUp",
          "X": 0.5578324794769287,
          "Y": 0.49499833583831787
        },
        {
          "Type": "mouthDown",
          "X": 0.5581704378128052,
          "Y": 0.4977799654006958
        },
        {
          "Type": "leftPupil",
          "X": 0.5566689968109131,
          "Y": 0.48642125725746155
        },
        {
          "Type": "rightPupil",
          "X": 0.5600599646568298,
          "Y": 0.48639577627182007
        },
        {
          "Type": "upperJawlineLeft",
          "X": 0.5575846433639526,
          "Y": 0.48643532395362854
        },
        {
          "Type": "midJawlineLeft",
          "X": 0.5580594539642334,
          "Y": 0.4963238537311554
        },
        {
          "Type": "chinBottom",
          "X": 0.5590728521347046,
          "Y": 0.5023376941680908
        },
        {
          "Type": "midJawlineRight",
          "X": 0.5644678473472595,
          "Y": 0.4964243471622467
        },
        {
          "Type": "upperJawlineRight",
          "X": 0.5653010606765747,
          "Y": 0.4864640235900879
        }
      ],
      "Pose": {
        "Roll": -39.9677848815918,
        "Yaw": -11.995777130126953,
        "Pitch": -2.8331525325775146
      },
      "Quality": {
        "Brightness": 82.72058868408203,
        "Sharpness": 0.4386158287525177
      },
      "Confidence": 61.64712905883789
    },
    {
      "BoundingBox": {
        "Width": 0.009168711490929127,
        "Height": 0.01920362561941147,
        "Left": 0.473844975233078,
        "Top": 0.460064560174942
      },
      "AgeRange": {
        "Low": 9,
        "High": 17
      },
      "Smile": {
        "Value": false,
        "Confidence": 93.23374938964844
      },
      "Eyeglasses": {
        "Value": false,
        "Confidence": 97.2623519897461
      },
      "Sunglasses": {
        "Value": false,
        "Confidence": 99.9964828491211
      },
      "Gender": {
        "Value": "Female",
        "Confidence": 78.84300231933594
      },
      "Beard": {
        "Value": false,
        "Confidence": 80.20384216308594
      },
      "Mustache": {
        "Value": false,
        "Confidence": 94.42351531982422
      },
      "EyesOpen": {
        "Value": false,
        "Confidence": 99.93215942382812
      },
      "MouthOpen": {
        "Value": false,
        "Confidence": 84.68602752685547
      },
      "Emotions": [
        {
          "Type": "CALM",
          "Confidence": 79.71527862548828
        },
        {
          "Type": "SURPRISED",
          "Confidence": 8.023025512695312
        },
        {
          "Type": "CONFUSED",
          "Confidence": 6.953284740447998
        },
        {
          "Type": "FEAR",
          "Confidence": 6.441549777984619
        },
        {
          "Type": "ANGRY",
          "Confidence": 4.042990207672119
        },
        {
          "Type": "SAD",
          "Confidence": 2.995105743408203
        },
        {
          "Type": "DISGUSTED",
          "Confidence": 1.1915487051010132
        },
        {
          "Type": "HAPPY",
          "Confidence": 1.126383662223816
        }
      ],
      "Landmarks": [
        {
          "Type": "eyeLeft",
          "X": 0.47787657380104065,
          "Y": 0.46639391779899597
        },
        {
          "Type": "eyeRight",
          "X": 0.48099157214164734,
          "Y": 0.4687356948852539
        },
        {
          "Type": "mouthLeft",
          "X": 0.47605177760124207,
          "Y": 0.4742967486381531
        },
        {
          "Type": "mouthRight",
          "X": 0.47865599393844604,
          "Y": 0.47622939944267273
        },
        {
          "Type": "nose",
          "X": 0.47826293110847473,
          "Y": 0.47158026695251465
        },
        {
          "Type": "leftEyeBrowLeft",
          "X": 0.4772261381149292,
          "Y": 0.4639925956726074
        },
        {
          "Type": "leftEyeBrowRight",
          "X": 0.4791146218776703,
          "Y": 0.4647931158542633
        },
        {
          "Type": "leftEyeBrowUp",
          "X": 0.4783155024051666,
          "Y": 0.46373265981674194
        },
        {
          "Type": "rightEyeBrowLeft",
          "X": 0.4809427261352539,
          "Y": 0.4661700427532196
        },
        {
          "Type": "rightEyeBrowRight",
          "X": 0.4827010929584503,
          "Y": 0.4681694507598877
        },
        {
          "Type": "rightEyeBrowUp",
          "X": 0.481990784406662,
          "Y": 0.4665158689022064
        },
        {
          "Type": "leftEyeLeft",
          "X": 0.4773428440093994,
          "Y": 0.46598753333091736
        },
        {
          "Type": "leftEyeRight",
          "X": 0.4784899652004242,
          "Y": 0.46698835492134094
        },
        {
          "Type": "leftEyeUp",
          "X": 0.4779689908027649,
          "Y": 0.4660302698612213
        },
        {
          "Type": "leftEyeDown",
          "X": 0.4778051972389221,
          "Y": 0.4667753577232361
        },
        {
          "Type": "rightEyeLeft",
          "X": 0.4803735017776489,
          "Y": 0.46841195225715637
        },
        {
          "Type": "rightEyeRight",
          "X": 0.4815959632396698,
          "Y": 0.46919745206832886
        },
        {
          "Type": "rightEyeUp",
          "X": 0.48111289739608765,
          "Y": 0.4684007167816162
        },
        {
          "Type": "rightEyeDown",
          "X": 0.4809070825576782,
          "Y": 0.46911299228668213
        },
        {
          "Type": "noseLeft",
          "X": 0.4775141775608063,
          "Y": 0.47196537256240845
        },
        {
          "Type": "noseRight",
          "X": 0.47870996594429016,
          "Y": 0.47286832332611084
        },
        {
          "Type": "mouthUp",
          "X": 0.47760647535324097,
          "Y": 0.4741608500480652
        },
        {
          "Type": "mouthDown",
          "X": 0.4770165681838989,
          "Y": 0.4764118790626526
        },
        {
          "Type": "leftPupil",
          "X": 0.47787657380104065,
          "Y": 0.46639391779899597
        },
        {
          "Type": "rightPupil",
          "X": 0.48099157214164734,
          "Y": 0.4687356948852539
        },
        {
          "Type": "upperJawlineLeft",
          "X": 0.4761231541633606,
          "Y": 0.46550682187080383
        },
        {
          "Type": "midJawlineLeft",
          "X": 0.4745117127895355,
          "Y": 0.4737330675125122
        },
        {
          "Type": "chinBottom",
          "X": 0.47601595520973206,
          "Y": 0.4801752269268036
        },
        {
          "Type": "midJawlineRight",
          "X": 0.48023393750190735,
          "Y": 0.47811514139175415
        },
        {
          "Type": "upperJawlineRight",
          "X": 0.48307785391807556,
          "Y": 0.4708283245563507
        }
      ],
      "Pose": {
        "Roll": -58.58506774902344,
        "Yaw": -5.375870704650879,
        "Pitch": -3.704634428024292
      },
      "Quality": {
        "Brightness": 64.03091430664062,
        "Sharpness": 0.4386158287525177
      },
      "Confidence": 86.30138397216797
    },
    {
      "BoundingBox": {
        "Width": 0.009375830180943012,
        "Height": 0.01835598796606064,
        "Left": 0.41898801922798157,
        "Top": 0.4377001225948334
      },
      "AgeRange": {
        "Low": 11,
        "High": 19
      },
      "Smile": {
        "Value": false,
        "Confidence": 91.09708404541016
      },
      "Eyeglasses": {
        "Value": false,
        "Confidence": 95.90266418457031
      },
      "Sunglasses": {
        "Value": false,
        "Confidence": 99.99565124511719
      },
      "Gender": {
        "Value": "Male",
        "Confidence": 89.3857421875
      },
      "Beard": {
        "Value": false,
        "Confidence": 72.31636047363281
      },
      "Mustache": {
        "Value": false,
        "Confidence": 91.9287338256836
      },
      "EyesOpen": {
        "Value": false,
        "Confidence": 99.52812957763672
      },
      "MouthOpen": {
        "Value": false,
        "Confidence": 74.22453308105469
      },
      "Emotions": [
        {
          "Type": "ANGRY",
          "Confidence": 32.731101989746094
        },
        {
          "Type": "CALM",
          "Confidence": 25.21834945678711
        },
        {
          "Type": "SURPRISED",
          "Confidence": 15.292267799377441
        },
        {
          "Type": "DISGUSTED",
          "Confidence": 12.944525718688965
        },
        {
          "Type": "FEAR",
          "Confidence": 6.829029083251953
        },
        {
          "Type": "CONFUSED",
          "Confidence": 6.369039535522461
        },
        {
          "Type": "SAD",
          "Confidence": 5.522101879119873
        },
        {
          "Type": "HAPPY",
          "Confidence": 1.9251846075057983
        }
      ],
      "Landmarks": [
        {
          "Type": "eyeLeft",
          "X": 0.4229237735271454,
          "Y": 0.4432656764984131
        },
        {
          "Type": "eyeRight",
          "X": 0.425508052110672,
          "Y": 0.4459301233291626
        },
        {
          "Type": "mouthLeft",
          "X": 0.42094680666923523,
          "Y": 0.4497568905353546
        },
        {
          "Type": "mouthRight",
          "X": 0.4231129288673401,
          "Y": 0.45196324586868286
        },
        {
          "Type": "nose",
          "X": 0.42275357246398926,
          "Y": 0.4475213885307312
        },
        {
          "Type": "leftEyeBrowLeft",
          "X": 0.42259082198143005,
          "Y": 0.4411260783672333
        },
        {
          "Type": "leftEyeBrowRight",
          "X": 0.424011766910553,
          "Y": 0.4419843256473541
        },
        {
          "Type": "leftEyeBrowUp",
          "X": 0.42341944575309753,
          "Y": 0.4409611225128174
        },
        {
          "Type": "rightEyeBrowLeft",
          "X": 0.42553067207336426,
          "Y": 0.4435392916202545
        },
        {
          "Type": "rightEyeBrowRight",
          "X": 0.42713281512260437,
          "Y": 0.4458661675453186
        },
        {
          "Type": "rightEyeBrowUp",
          "X": 0.4264706075191498,
          "Y": 0.4441065490245819
        },
        {
          "Type": "leftEyeLeft",
          "X": 0.4225212633609772,
          "Y": 0.4428342580795288
        },
        {
          "Type": "leftEyeRight",
          "X": 0.4234345853328705,
          "Y": 0.4438975751399994
        },
        {
          "Type": "leftEyeUp",
          "X": 0.42301371693611145,
          "Y": 0.44294336438179016
        },
        {
          "Type": "leftEyeDown",
          "X": 0.42284780740737915,
          "Y": 0.44357380270957947
        },
        {
          "Type": "rightEyeLeft",
          "X": 0.4249979257583618,
          "Y": 0.4455157518386841
        },
        {
          "Type": "rightEyeRight",
          "X": 0.42604774236679077,
          "Y": 0.4464830458164215
        },
        {
          "Type": "rightEyeUp",
          "X": 0.42562225461006165,
          "Y": 0.44563743472099304
        },
        {
          "Type": "rightEyeDown",
          "X": 0.4254198670387268,
          "Y": 0.44623324275016785
        },
        {
          "Type": "noseLeft",
          "X": 0.4222363829612732,
          "Y": 0.44789960980415344
        },
        {
          "Type": "noseRight",
          "X": 0.4232269823551178,
          "Y": 0.44892075657844543
        },
        {
          "Type": "mouthUp",
          "X": 0.4221763610839844,
          "Y": 0.44980525970458984
        },
        {
          "Type": "mouthDown",
          "X": 0.4215870499610901,
          "Y": 0.4516928195953369
        },
        {
          "Type": "leftPupil",
          "X": 0.4229237735271454,
          "Y": 0.4432656764984131
        },
        {
          "Type": "rightPupil",
          "X": 0.425508052110672,
          "Y": 0.4459301233291626
        },
        {
          "Type": "upperJawlineLeft",
          "X": 0.42187008261680603,
          "Y": 0.4425923824310303
        },
        {
          "Type": "midJawlineLeft",
          "X": 0.41997674107551575,
          "Y": 0.44940486550331116
        },
        {
          "Type": "chinBottom",
          "X": 0.4206237494945526,
          "Y": 0.45492318272590637
        },
        {
          "Type": "midJawlineRight",
          "X": 0.4247150421142578,
          "Y": 0.4543491303920746
        },
        {
          "Type": "upperJawlineRight",
          "X": 0.4276387393474579,
          "Y": 0.4486103355884552
        }
      ],
      "Pose": {
        "Roll": -27.74955177307129,
        "Yaw": -5.430093765258789,
        "Pitch": 3.470564842224121
      },
      "Quality": {
        "Brightness": 50.72022247314453,
        "Sharpness": 0.4386158287525177
      },
      "Confidence": 78.78716278076172
    }
  ],
  "Labels": [
    {
      "Name": "Person",
      "Confidence": 99.35718536376953,
      "Instances": [
        {
          "BoundingBox": {
            "Width": 0.3157227039337158,
            "Height": 0.5882026553153992,
            "Left": 0.09773935377597809,
            "Top": 0.4022699296474457
          },
          "Confidence": 99.35718536376953
        },
        {
          "BoundingBox": {
            "Width": 0.38258859515190125,
            "Height": 0.6593957543373108,
            "Left": 0.47296255826950073,
            "Top": 0.33786454796791077
          },
          "Confidence": 98.8306655883789
        },
        {
          "BoundingBox": {
            "Width": 0.1739940643310547,
            "Height": 0.5371106863021851,
            "Left": 0,
            "Top": 0.4351963698863983
          },
          "Confidence": 98.37611389160156
        },
        {
          "BoundingBox": {
            "Width": 0.04613679647445679,
            "Height": 0.23411312699317932,
            "Left": 0.7281667590141296,
            "Top": 0.22167760133743286
          },
          "Confidence": 98.27887725830078
        },
        {
          "BoundingBox": {
            "Width": 0.18042923510074615,
            "Height": 0.657301664352417,
            "Left": 0.7715386748313904,
            "Top": 0.3231201469898224
          },
          "Confidence": 98.20667266845703
        },
        {
          "BoundingBox": {
            "Width": 0.08677742630243301,
            "Height": 0.6440168619155884,
            "Left": 0.9114682078361511,
            "Top": 0.34096989035606384
          },
          "Confidence": 96.27974700927734
        },
        {
          "BoundingBox": {
            "Width": 0.03028462640941143,
            "Height": 0.0657183900475502,
            "Left": 0.4011431634426117,
            "Top": 0.4316266179084778
          },
          "Confidence": 92.01349639892578
        },
        {
          "BoundingBox": {
            "Width": 0.05306043103337288,
            "Height": 0.16265743970870972,
            "Left": 0.3285071551799774,
            "Top": 0.36200323700904846
          },
          "Confidence": 77.22628784179688
        },
        {
          "BoundingBox": {
            "Width": 0.06685298681259155,
            "Height": 0.2538212835788727,
            "Left": 0.7576054930686951,
            "Top": 0.23402060568332672
          },
          "Confidence": 77.10749816894531
        },
        {
          "BoundingBox": {
            "Width": 0.030899958685040474,
            "Height": 0.07117242366075516,
            "Left": 0.8339411020278931,
            "Top": 0.2593792974948883
          },
          "Confidence": 46.419002532958984
        },
        {
          "BoundingBox": {
            "Width": 0.06735561788082123,
            "Height": 0.1893809735774994,
            "Left": 0.4047299027442932,
            "Top": 0.43812522292137146
          },
          "Confidence": 42.13547897338867
        }
      ],
      "Parents": []
    },
    {
      "Name": "Human",
      "Confidence": 99.35718536376953,
      "Instances": [],
      "Parents": []
    },
    {
      "Name": "Helmet",
      "Confidence": 97.93828582763672,
      "Instances": [
        {
          "BoundingBox": {
            "Width": 0.18516916036605835,
            "Height": 0.25708165764808655,
            "Left": 0.16618788242340088,
            "Top": 0.40895700454711914
          },
          "Confidence": 97.93828582763672
        }
      ],
      "Parents": [
        {
          "Name": "Clothing"
        }
      ]
    },
    {
      "Name": "Clothing",
      "Confidence": 97.93828582763672,
      "Instances": [],
      "Parents": []
    },
    {
      "Name": "Apparel",
      "Confidence": 97.93828582763672,
      "Instances": [],
      "Parents": []
    },
    {
      "Name": "Police",
      "Confidence": 95.09339904785156,
      "Instances": [],
      "Parents": [
        {
          "Name": "Person"
        }
      ]
    },
    {
      "Name": "Tie",
      "Confidence": 89.05889129638672,
      "Instances": [
        {
          "BoundingBox": {
            "Width": 0.015371864661574364,
            "Height": 0.08395310491323471,
            "Left": 0.8636114001274109,
            "Top": 0.44006267189979553
          },
          "Confidence": 89.05889129638672
        }
      ],
      "Parents": [
        {
          "Name": "Accessories"
        }
      ]
    },
    {
      "Name": "Accessories",
      "Confidence": 89.05889129638672,
      "Instances": [],
      "Parents": []
    },
    {
      "Name": "Accessory",
      "Confidence": 89.05889129638672,
      "Instances": [],
      "Parents": []
    },
    {
      "Name": "Military Uniform",
      "Confidence": 75.24251556396484,
      "Instances": [],
      "Parents": [
        {
          "Name": "Military"
        }
      ]
    },
    {
      "Name": "Military",
      "Confidence": 75.24251556396484,
      "Instances": [],
      "Parents": []
    },
    {
      "Name": "Crowd",
      "Confidence": 74.34935760498047,
      "Instances": [],
      "Parents": [
        {
          "Name": "Person"
        }
      ]
    },
    {
      "Name": "Officer",
      "Confidence": 72.00431060791016,
      "Instances": [],
      "Parents": [
        {
          "Name": "Person"
        },
        {
          "Name": "Military Uniform"
        },
        {
          "Name": "Military"
        }
      ]
    },
    {
      "Name": "Funeral",
      "Confidence": 59.123043060302734,
      "Instances": [],
      "Parents": [
        {
          "Name": "Person"
        }
      ]
    },
    {
      "Name": "Coat",
      "Confidence": 56.3121223449707,
      "Instances": [],
      "Parents": [
        {
          "Name": "Clothing"
        }
      ]
    }
  ],
  "LabelModelVersion": "2.0"
}