{
  "FaceDetails": [],
  "Labels": [
    {
      "Name": "Label",
      "Confidence": 99.83138275146484,
      "Instances": [],
      "Parents": [
        {
          "Name": "Text"
        }
      ]
    },
    {
      "Name": "Text",
      "Confidence": 99.83138275146484,
      "Instances": [],
      "Parents": []
    },
    {
      "Name": "Concrete",
      "Confidence": 87.88967895507812,
      "Instances": [],
      "Parents": []
    },
    {
      "Name": "Sticker",
      "Confidence": 72.93738555908203,
      "Instances": [],
      "Parents": [
        {
          "Name": "Label"
        },
        {
          "Name": "Text"
        }
      ]
    },
    {
      "Name": "Tarmac",
      "Confidence": 71.34089660644531,
      "Instances": [],
      "Parents": []
    },
    {
      "Name": "Asphalt",
      "Confidence": 71.34089660644531,
      "Instances": [],
      "Parents": []
    },
    {
      "Name": "Poster",
      "Confidence": 66.68339538574219,
      "Instances": [],
      "Parents": [
        {
          "Name": "Advertisement"
        }
      ]
    },
    {
      "Name": "Advertisement",
      "Confidence": 66.68339538574219,
      "Instances": [],
      "Parents": []
    },
    {
      "Name": "Tar",
      "Confidence": 59.490234375,
      "Instances": [],
      "Parents": []
    },
    {
      "Name": "Brick",
      "Confidence": 58.732078552246094,
      "Instances": [],
      "Parents": []
    }
  ],
  "LabelModelVersion": "2.0"
}