{
  "FaceDetails": [
    {
      "BoundingBox": {
        "Width": 0.0837005227804184,
        "Height": 0.21985208988189697,
        "Left": 0.11347339302301407,
        "Top": 0.39864861965179443
      },
      "AgeRange": {
        "Low": 26,
        "High": 36
      },
      "Smile": {
        "Value": false,
        "Confidence": 95.07997131347656
      },
      "Eyeglasses": {
        "Value": false,
        "Confidence": 97.74325561523438
      },
      "Sunglasses": {
        "Value": false,
        "Confidence": 99.99673461914062
      },
      "Gender": {
        "Value": "Female",
        "Confidence": 98.43763732910156
      },
      "Beard": {
        "Value": false,
        "Confidence": 89.8048324584961
      },
      "Mustache": {
        "Value": false,
        "Confidence": 97.7558822631836
      },
      "EyesOpen": {
        "Value": false,
        "Confidence": 99.99691009521484
      },
      "MouthOpen": {
        "Value": false,
        "Confidence": 93.24036407470703
      },
      "Emotions": [
        {
          "Type": "CALM",
          "Confidence": 99.83821868896484
        },
        {
          "Type": "SURPRISED",
          "Confidence": 6.255543231964111
        },
        {
          "Type": "FEAR",
          "Confidence": 5.878985404968262
        },
        {
          "Type": "SAD",
          "Confidence": 2.172830581665039
        },
        {
          "Type": "DISGUSTED",
          "Confidence": 0.026685215532779694
        },
        {
          "Type": "CONFUSED",
          "Confidence": 0.015040941536426544
        },
        {
          "Type": "ANGRY",
          "Confidence": 0.009564004838466644
        },
        {
          "Type": "HAPPY",
          "Confidence": 0.005341992247849703
        }
      ],
      "Landmarks": [
        {
          "Type": "eyeLeft",
          "X": 0.16598205268383026,
          "Y": 0.4924090504646301
        },
        {
          "Type": "eyeRight",
          "X": 0.17076708376407623,
          "Y": 0.4973643124103546
        },
        {
          "Type": "mouthLeft",
          "X": 0.16786006093025208,
          "Y": 0.5685533881187439
        },
        {
          "Type": "mouthRight",
          "X": 0.17104940116405487,
          "Y": 0.5717490315437317
        },
        {
          "Type": "nose",
          "X": 0.1943524330854416,
          "Y": 0.5315379500389099
        },
        {
          "Type": "leftEyeBrowLeft",
          "X": 0.1539068967103958,
          "Y": 0.4769892990589142
        },
        {
          "Type": "leftEyeBrowRight",
          "X": 0.17517711222171783,
          "Y": 0.47347864508628845
        },
        {
          "Type": "leftEyeBrowUp",
          "X": 0.16832324862480164,
          "Y": 0.4689960479736328
        },
        {
          "Type": "rightEyeBrowLeft",
          "X": 0.1794915646314621,
          "Y": 0.4767422080039978
        },
        {
          "Type": "rightEyeBrowRight",
          "X": 0.16554386913776398,
          "Y": 0.4858199656009674
        },
        {
          "Type": "rightEyeBrowUp",
          "X": 0.17709670960903168,
          "Y": 0.47529780864715576
        },
        {
          "Type": "leftEyeLeft",
          "X": 0.16123035550117493,
          "Y": 0.4920569360256195
        },
        {
          "Type": "leftEyeRight",
          "X": 0.1667589247226715,
          "Y": 0.4943726658821106
        },
        {
          "Type": "leftEyeUp",
          "X": 0.16696734726428986,
          "Y": 0.488985538482666
        },
        {
          "Type": "leftEyeDown",
          "X": 0.16584113240242004,
          "Y": 0.4958345592021942
        },
        {
          "Type": "rightEyeLeft",
          "X": 0.16993167996406555,
          "Y": 0.49750059843063354
        },
        {
          "Type": "rightEyeRight",
          "X": 0.16905975341796875,
          "Y": 0.4984988868236542
        },
        {
          "Type": "rightEyeUp",
          "X": 0.17246323823928833,
          "Y": 0.4939955174922943
        },
        {
          "Type": "rightEyeDown",
          "X": 0.17124971747398376,
          "Y": 0.500495195388794
        },
        {
          "Type": "noseLeft",
          "X": 0.17676983773708344,
          "Y": 0.5377299785614014
        },
        {
          "Type": "noseRight",
          "X": 0.1799706369638443,
          "Y": 0.5392433404922485
        },
        {
          "Type": "mouthUp",
          "X": 0.18063566088676453,
          "Y": 0.5548747181892395
        },
        {
          "Type": "mouthDown",
          "X": 0.17707672715187073,
          "Y": 0.5754930973052979
        },
        {
          "Type": "leftPupil",
          "X": 0.16598205268383026,
          "Y": 0.4924090504646301
        },
        {
          "Type": "rightPupil",
          "X": 0.17076708376407623,
          "Y": 0.4973643124103546
        },
        {
          "Type": "upperJawlineLeft",
          "X": 0.12071245163679123,
          "Y": 0.4975035786628723
        },
        {
          "Type": "midJawlineLeft",
          "X": 0.1254854053258896,
          "Y": 0.5685339570045471
        },
        {
          "Type": "chinBottom",
          "X": 0.16558939218521118,
          "Y": 0.6094322800636292
        },
        {
          "Type": "midJawlineRight",
          "X": 0.14243870973587036,
          "Y": 0.5765159130096436
        },
        {
          "Type": "upperJawlineRight",
          "X": 0.1384984701871872,
          "Y": 0.5088294148445129
        }
      ],
      "Pose": {
        "Roll": 37.27003860473633,
        "Yaw": 82.80387115478516,
        "Pitch": 32.92011260986328
      },
      "Quality": {
        "Brightness": 31.254989624023438,
        "Sharpness": 5.775668621063232
      },
      "Confidence": 99.88589477539062
    },
    {
      "BoundingBox": {
        "Width": 0.09577684849500656,
        "Height": 0.18852779269218445,
        "Left": 0.5087385773658752,
        "Top": 0.42430785298347473
      },
      "AgeRange": {
        "Low": 23,
        "High": 31
      },
      "Smile": {
        "Value": true,
        "Confidence": 81.23797607421875
      },
      "Eyeglasses": {
        "Value": false,
        "Confidence": 97.57421112060547
      },
      "Sunglasses": {
        "Value": false,
        "Confidence": 99.99663543701172
      },
      "Gender": {
        "Value": "Female",
        "Confidence": 99.93077087402344
      },
      "Beard": {
        "Value": false,
        "Confidence": 91.34623718261719
      },
      "Mustache": {
        "Value": false,
        "Confidence": 98.19237518310547
      },
      "EyesOpen": {
        "Value": true,
        "Confidence": 97.48377990722656
      },
      "MouthOpen": {
        "Value": false,
        "Confidence": 87.53429412841797
      },
      "Emotions": [
        {
          "Type": "HAPPY",
          "Confidence": 98.82723999023438
        },
        {
          "Type": "SURPRISED",
          "Confidence": 6.352848052978516
        },
        {
          "Type": "FEAR",
          "Confidence": 5.908784866333008
        },
        {
          "Type": "SAD",
          "Confidence": 2.223900556564331
        },
        {
          "Type": "CONFUSED",
          "Confidence": 0.24599139392375946
        },
        {
          "Type": "CALM",
          "Confidence": 0.1952800154685974
        },
        {
          "Type": "ANGRY",
          "Confidence": 0.11794598400592804
        },
        {
          "Type": "DISGUSTED",
          "Confidence": 0.07089442014694214
        }
      ],
      "Landmarks": [
        {
          "Type": "eyeLeft",
          "X": 0.5552523136138916,
          "Y": 0.5012719035148621
        },
        {
          "Type": "eyeRight",
          "X": 0.5912986397743225,
          "Y": 0.49258288741111755
        },
        {
          "Type": "mouthLeft",
          "X": 0.5585340857505798,
          "Y": 0.5661758184432983
        },
        {
          "Type": "mouthRight",
          "X": 0.5887461304664612,
          "Y": 0.558452844619751
        },
        {
          "Type": "nose",
          "X": 0.5876908898353577,
          "Y": 0.5365914106369019
        },
        {
          "Type": "leftEyeBrowLeft",
          "X": 0.5359631180763245,
          "Y": 0.4882586598396301
        },
        {
          "Type": "leftEyeBrowRight",
          "X": 0.5671316981315613,
          "Y": 0.4819790720939636
        },
        {
          "Type": "leftEyeBrowUp",
          "X": 0.553929328918457,
          "Y": 0.4800736904144287
        },
        {
          "Type": "rightEyeBrowLeft",
          "X": 0.5878697037696838,
          "Y": 0.47765985131263733
        },
        {
          "Type": "rightEyeBrowRight",
          "X": 0.5987908244132996,
          "Y": 0.47387072443962097
        },
        {
          "Type": "rightEyeBrowUp",
          "X": 0.5956748723983765,
          "Y": 0.4711467921733856
        },
        {
          "Type": "leftEyeLeft",
          "X": 0.5467950701713562,
          "Y": 0.5019785165786743
        },
        {
          "Type": "leftEyeRight",
          "X": 0.5621266961097717,
          "Y": 0.5002824068069458
        },
        {
          "Type": "leftEyeUp",
          "X": 0.5557401180267334,
          "Y": 0.49827292561531067
        },
        {
          "Type": "leftEyeDown",
          "X": 0.5552908778190613,
          "Y": 0.5042689442634583
        },
        {
          "Type": "rightEyeLeft",
          "X": 0.5838932991027832,
          "Y": 0.49514663219451904
        },
        {
          "Type": "rightEyeRight",
          "X": 0.5957658886909485,
          "Y": 0.4903748333454132
        },
        {
          "Type": "rightEyeUp",
          "X": 0.5919896960258484,
          "Y": 0.48974379897117615
        },
        {
          "Type": "rightEyeDown",
          "X": 0.591072142124176,
          "Y": 0.49569597840309143
        },
        {
          "Type": "noseLeft",
          "X": 0.5720004439353943,
          "Y": 0.5424517393112183
        },
        {
          "Type": "noseRight",
          "X": 0.5854880213737488,
          "Y": 0.5394391417503357
        },
        {
          "Type": "mouthUp",
          "X": 0.5801467299461365,
          "Y": 0.5567420125007629
        },
        {
          "Type": "mouthDown",
          "X": 0.5782545208930969,
          "Y": 0.5756791234016418
        },
        {
          "Type": "leftPupil",
          "X": 0.5552523136138916,
          "Y": 0.5012719035148621
        },
        {
          "Type": "rightPupil",
          "X": 0.5912986397743225,
          "Y": 0.49258288741111755
        },
        {
          "Type": "upperJawlineLeft",
          "X": 0.5106697678565979,
          "Y": 0.5005289912223816
        },
        {
          "Type": "midJawlineLeft",
          "X": 0.5217775702476501,
          "Y": 0.569215714931488
        },
        {
          "Type": "chinBottom",
          "X": 0.5724430680274963,
          "Y": 0.6068460941314697
        },
        {
          "Type": "midJawlineRight",
          "X": 0.5861129760742188,
          "Y": 0.5551535487174988
        },
        {
          "Type": "upperJawlineRight",
          "X": 0.5896215438842773,
          "Y": 0.4832707643508911
        }
      ],
      "Pose": {
        "Roll": -11.557016372680664,
        "Yaw": 28.349693298339844,
        "Pitch": -21.85761833190918
      },
      "Quality": {
        "Brightness": 35.48554611206055,
        "Sharpness": 5.775668621063232
      },
      "Confidence": 99.99247741699219
    }
  ],
  "Labels": [
    {
      "Name": "Person",
      "Confidence": 99.40707397460938,
      "Instances": [
        {
          "BoundingBox": {
            "Width": 0.3443908989429474,
            "Height": 0.6364684104919434,
            "Left": 0.30518388748168945,
            "Top": 0.3453678786754608
          },
          "Confidence": 99.40707397460938
        },
        {
          "BoundingBox": {
            "Width": 0.27800917625427246,
            "Height": 0.606164813041687,
            "Left": 0.016810769215226173,
            "Top": 0.36972832679748535
          },
          "Confidence": 98.94956970214844
        }
      ],
      "Parents": []
    },
    {
      "Name": "Human",
      "Confidence": 99.40707397460938,
      "Instances": [],
      "Parents": []
    },
    {
      "Name": "Face",
      "Confidence": 98.85492706298828,
      "Instances": [],
      "Parents": [
        {
          "Name": "Person"
        }
      ]
    },
    {
      "Name": "Studio",
      "Confidence": 89.05526733398438,
      "Instances": [],
      "Parents": []
    },
    {
      "Name": "Portrait",
      "Confidence": 78.55785369873047,
      "Instances": [],
      "Parents": [
        {
          "Name": "Face"
        },
        {
          "Name": "Photography"
        },
        {
          "Name": "Person"
        }
      ]
    },
    {
      "Name": "Photography",
      "Confidence": 78.55785369873047,
      "Instances": [],
      "Parents": [
        {
          "Name": "Person"
        }
      ]
    },
    {
      "Name": "Photo",
      "Confidence": 78.55785369873047,
      "Instances": [],
      "Parents": [
        {
          "Name": "Person"
        }
      ]
    },
    {
      "Name": "Clothing",
      "Confidence": 66.54426574707031,
      "Instances": [],
      "Parents": []
    },
    {
      "Name": "Apparel",
      "Confidence": 66.54426574707031,
      "Instances": [],
      "Parents": []
    },
    {
      "Name": "Meal",
      "Confidence": 62.1600456237793,
      "Instances": [],
      "Parents": [
        {
          "Name": "Food"
        }
      ]
    },
    {
      "Name": "Food",
      "Confidence": 62.1600456237793,
      "Instances": [],
      "Parents": []
    },
    {
      "Name": "Smile",
      "Confidence": 59.8586540222168,
      "Instances": [],
      "Parents": [
        {
          "Name": "Face"
        },
        {
          "Name": "Person"
        }
      ]
    },
    {
      "Name": "Female",
      "Confidence": 59.78127670288086,
      "Instances": [],
      "Parents": [
        {
          "Name": "Person"
        }
      ]
    },
    {
      "Name": "Dish",
      "Confidence": 59.2972526550293,
      "Instances": [],
      "Parents": [
        {
          "Name": "Meal"
        },
        {
          "Name": "Food"
        }
      ]
    },
    {
      "Name": "Skin",
      "Confidence": 57.36820602416992,
      "Instances": [],
      "Parents": []
    },
    {
      "Name": "Electronics",
      "Confidence": 55.8994255065918,
      "Instances": [],
      "Parents": []
    }
  ],
  "LabelModelVersion": "2.0"
}